django_restresp-0.1.8.dist-info/DESCRIPTION.rst
django_restresp-0.1.8.dist-info/METADATA
django_restresp-0.1.8.dist-info/RECORD
django_restresp-0.1.8.dist-info/WHEEL
django_restresp-0.1.8.dist-info/metadata.json
django_restresp-0.1.8.dist-info/top_level.txt
restresp/__init__.py
restresp/admin.py
restresp/apps.py
restresp/helpers.py
restresp/models.py
restresp/tests.py
restresp/views.py
